captcha/__init__.py
captcha/pdisk.py
captcha/type.py
img_captcha-0.0.1.dist-info/LICENSE
img_captcha-0.0.1.dist-info/METADATA
img_captcha-0.0.1.dist-info/WHEEL
img_captcha-0.0.1.dist-info/top_level.txt
img_captcha-0.0.1.dist-info/RECORD
