Metadata-Version: 2.1
Name: img-captcha
Version: 0.0.1
Summary: An Unofficial Asynchronous Python version of pdisk API wrapper
Author-email: kalanakt <kalanakt@nodevision.agency>
Project-URL: Homepage, https://github.com/kalanakt/pdisk
Project-URL: Bug Tracker, https://github.com/kalanakt/pdisk/issues
Classifier: Programming Language :: Python :: 3
Classifier: License :: OSI Approved :: MIT License
Classifier: Operating System :: OS Independent
Requires-Python: >=3.7
License-File: LICENSE
